{
  "_class": "group",
  "do_objectID": "0C1AEA3A-B5F2-4336-83F7-3E093AC63A1E",
  "exportOptions": {
    "_class": "exportOptions",
    "exportFormats": [
    ],
    "includedLayerIds": [
    ],
    "layerOptions": 0,
    "shouldTrim": false
  },
  "frame": {
    "_class": "rect",
    "constrainProportions": false,
    "height": 21,
    "width": 48,
    "x": 146,
    "y": 0
  },
  "hasClickThrough": false,
  "isFlippedHorizontal": false,
  "isFlippedVertical": false,
  "isLocked": false,
  "isVisible": true,
  "layerListExpandedType": 1,
  "layers": [
    {
      "class": "shapeGroup",
      "id": "3B9D99AB-1622-410C-B6D8-A6EBF8D81507"
    },
    {
      "class": "text",
      "id": "68ACDDC8-6E10-4EAD-9FD4-2B754CB80858"
    }
  ],
  "name": "Group 2",
  "nameIsFixed": false,
  "resizingConstraint": 63,
  "resizingType": 0,
  "rotation": 0,
  "shouldBreakMaskChain": false,
  "style": {
    "_class": "style",
    "endDecorationType": 0,
    "miterLimit": 10,
    "startDecorationType": 0
  }
}