{
  "_class": "artboard",
  "backgroundColor": {
    "_class": "color",
    "alpha": 1,
    "blue": 1,
    "green": 1,
    "red": 1
  },
  "do_objectID": "45D1C5F4-392A-44C3-AA0C-52685B3186DD",
  "exportOptions": {
    "_class": "exportOptions",
    "exportFormats": [
    ],
    "includedLayerIds": [
    ],
    "layerOptions": 0,
    "shouldTrim": false
  },
  "frame": {
    "_class": "rect",
    "constrainProportions": false,
    "height": 640,
    "width": 360,
    "x": 3337,
    "y": 1591
  },
  "hasBackgroundColor": false,
  "hasClickThrough": true,
  "horizontalRulerData": {
    "_class": "rulerData",
    "base": 0,
    "guides": [
    ]
  },
  "includeBackgroundColorInExport": true,
  "includeInCloudUpload": true,
  "isFlippedHorizontal": false,
  "isFlippedVertical": false,
  "isLocked": false,
  "isVisible": true,
  "layerListExpandedType": 2,
  "layers": [
    {
      "class": "symbolInstance",
      "id": "B1FBED05-234D-4003-A3A6-FCA28529FA94"
    },
    {
      "class": "shapeGroup",
      "id": "F17325BC-0689-4A2C-9F63-A1106498ADEC"
    },
    {
      "class": "symbolInstance",
      "id": "13C7D8EA-6610-4964-93FC-7E29DF82FC4C"
    },
    {
      "class": "symbolInstance",
      "id": "911BF2A2-10CF-496A-8410-B751C2EA13E8"
    },
    {
      "class": "text",
      "id": "27D596CF-43A9-4A4B-821F-2840FBE6C178"
    },
    {
      "class": "shapeGroup",
      "id": "1B061950-6BE9-428C-A883-AAF24236EACD"
    },
    {
      "class": "shapeGroup",
      "id": "7CBFBE2C-96F9-4236-A4AE-F10575CF0532"
    },
    {
      "class": "text",
      "id": "70413508-6CBB-47C3-B2AA-A91C30AACD54"
    },
    {
      "class": "text",
      "id": "3F9ABDAF-9512-4C86-896D-3CE26DC46C91"
    },
    {
      "class": "text",
      "id": "DAE8923D-C161-468F-B85D-D4594CDA068E"
    },
    {
      "class": "text",
      "id": "7E9E08A0-315C-4A5C-A6A0-2D140107C54C"
    },
    {
      "class": "text",
      "id": "EAE99654-EC95-4E5D-AE6F-91D4600E064D"
    },
    {
      "class": "text",
      "id": "40434A09-E748-49F9-BD8F-563B0D894F60"
    },
    {
      "class": "text",
      "id": "7B7418D6-F9AF-43A1-81AE-C281C6844B8B"
    },
    {
      "class": "bitmap",
      "id": "742B8616-8FBD-49A7-AE5C-DE73C22B3ADB"
    },
    {
      "class": "text",
      "id": "5B004E8A-A2DC-4D74-8D44-C79783735343"
    },
    {
      "class": "text",
      "id": "5982E813-758C-40D3-B71B-AB670CC45A55"
    },
    {
      "class": "group",
      "id": "21F11065-A2B3-4EC3-9A95-675D2C7B6290"
    },
    {
      "class": "shapeGroup",
      "id": "8248BC60-D621-48C7-8D1F-9D1FE3E5BA91"
    },
    {
      "class": "text",
      "id": "5473EB42-5B6B-48EE-B923-4C73FC7E48E4"
    },
    {
      "class": "group",
      "id": "649ED58A-9BB3-49B8-B64A-12CC876608EC"
    },
    {
      "class": "text",
      "id": "A89AC67D-AC0C-465E-99DA-AA8220B14117"
    },
    {
      "class": "text",
      "id": "65C00A72-ECD1-4904-83CD-2D1C903FA0DB"
    },
    {
      "class": "text",
      "id": "F4870025-60BB-4D17-80E8-85B065F73F61"
    },
    {
      "class": "text",
      "id": "B299AB99-B878-4D4D-A7E0-0369322D2F13"
    },
    {
      "class": "text",
      "id": "61974712-0580-42FC-A83A-0897E9EC0711"
    }
  ],
  "name": "Dish Page",
  "nameIsFixed": true,
  "resizesContent": false,
  "resizingConstraint": 63,
  "resizingType": 0,
  "rotation": 0,
  "shouldBreakMaskChain": false,
  "style": {
    "_class": "style",
    "endDecorationType": 0,
    "miterLimit": 10,
    "startDecorationType": 0
  },
  "verticalRulerData": {
    "_class": "rulerData",
    "base": 0,
    "guides": [
    ]
  }
}